MANIFEST.in
setup.cfg
setup.py
versioneer.py
catimg/__init__.py
catimg/__main__.py
catimg/_version.py
catimg/imgur.py
catimg/util.py
catimg.egg-info/PKG-INFO
catimg.egg-info/SOURCES.txt
catimg.egg-info/dependency_links.txt
catimg.egg-info/entry_points.txt
catimg.egg-info/not-zip-safe
catimg.egg-info/requires.txt
catimg.egg-info/top_level.txt