Metadata-Version: 1.1
Name: catimg
Version: 1.1
Summary: Print an image of a cat from Imgur to iTerm2.
Home-page: https://github.com/asmeurer/catimg
Author: Aaron Meurer
Author-email: asmeurer@gmail.com
License: MIT
Platform: UNKNOWN
Classifier: Environment :: MacOS X
Classifier: Operating System :: MacOS :: MacOS X
Classifier: Programming Language :: Python :: 3
